litestar_hotreload/__init__.py
litestar_hotreload/_notify.py
litestar_hotreload/_watch.py
litestar_hotreload/middleware.py
litestar_hotreload/plugin.py
litestar_hotreload/templates/hotreload.js
litestar_hotreload-0.1.0.dist-info/METADATA
litestar_hotreload-0.1.0.dist-info/WHEEL
litestar_hotreload-0.1.0.dist-info/entry_points.txt
litestar_hotreload-0.1.0.dist-info/RECORD
